fixdoc/__init__.py
fixdoc/cli.py
fixdoc/config.py
fixdoc/fix.py
fixdoc/formatter.py
fixdoc/git.py
fixdoc/markdown_parser.py
fixdoc/models.py
fixdoc/storage.py
fixdoc/sync_engine.py
fixdoc/terraform_parser.py
fixdoc/commands/__init__.py
fixdoc/commands/analyze.py
fixdoc/commands/capture.py
fixdoc/commands/capture_handlers.py
fixdoc/commands/delete.py
fixdoc/commands/edit.py
fixdoc/commands/manage.py
fixdoc/commands/search.py
fixdoc/commands/sync.py
fixdoc/parsers/__init__.py
fixdoc/parsers/base.py
fixdoc/parsers/kubernetes.py
fixdoc/parsers/router.py
fixdoc/parsers/terraform.py
fixdoc-0.0.1.dist-info/METADATA
fixdoc-0.0.1.dist-info/WHEEL
fixdoc-0.0.1.dist-info/entry_points.txt
fixdoc-0.0.1.dist-info/top_level.txt
fixdoc-0.0.1.dist-info/RECORD
